subtitle/__init__.py
subtitle/translator.py
translate_subtitle-0.1.3.dist-info/METADATA
translate_subtitle-0.1.3.dist-info/WHEEL
translate_subtitle-0.1.3.dist-info/entry_points.txt
translate_subtitle-0.1.3.dist-info/top_level.txt
translate_subtitle-0.1.3.dist-info/RECORD
