Metadata-Version: 2.1
Name: translate_subtitle
Version: 0.1.3
Summary: A tool to translate subtitle files using DeepSeek API.
Home-page: https://github.com/zcq100/translate-subtitle
Author: r1a
Author-email: i@r1a.co
Classifier: Programming Language :: Python :: 3
Classifier: License :: OSI Approved :: MIT License
Classifier: Operating System :: OS Independent
Requires-Python: >=3.6
Requires-Dist: requests>=2.25.1
